{
  "$schema": "https://raw.githubusercontent.com/spdx/spdx-spec/v2.2.1/schemas/spdx-schema.json",
  "spdxVersion": "SPDX-2.2",
  "dataLicense": "CC0-1.0",
  "SPDXID": "SPDXRef-DOCUMENT",
  "documentNamespace": "https://spdx.org/spdxdocs/boost-unordered-x64-linux-1.86.0-7cbd6429-bea6-4298-9a98-0869b6b8e6f9",
  "name": "boost-unordered:x64-linux@1.86.0 214f87f86cf7ceb916d860595b3d219466f590fee297bf83831ad9c01b919ad0",
  "creationInfo": {
    "creators": [
      "Tool: vcpkg-2025-03-22-d4dd14112c2026ee57e59f966ecfa3b9137bd143"
    ],
    "created": "2025-04-05T08:07:27Z"
  },
  "relationships": [
    {
      "spdxElementId": "SPDXRef-port",
      "relationshipType": "GENERATES",
      "relatedSpdxElement": "SPDXRef-binary"
    },
    {
      "spdxElementId": "SPDXRef-port",
      "relationshipType": "CONTAINS",
      "relatedSpdxElement": "SPDXRef-file-0"
    },
    {
      "spdxElementId": "SPDXRef-port",
      "relationshipType": "CONTAINS",
      "relatedSpdxElement": "SPDXRef-file-1"
    },
    {
      "spdxElementId": "SPDXRef-binary",
      "relationshipType": "GENERATED_FROM",
      "relatedSpdxElement": "SPDXRef-port"
    },
    {
      "spdxElementId": "SPDXRef-file-0",
      "relationshipType": "CONTAINED_BY",
      "relatedSpdxElement": "SPDXRef-port"
    },
    {
      "spdxElementId": "SPDXRef-file-1",
      "relationshipType": "CONTAINED_BY",
      "relatedSpdxElement": "SPDXRef-port"
    }
  ],
  "packages": [
    {
      "name": "boost-unordered",
      "SPDXID": "SPDXRef-port",
      "versionInfo": "1.86.0",
      "downloadLocation": "git+https://github.com/Microsoft/vcpkg@3016f6768a087d2f7a5629edae86d00c67191f1f",
      "homepage": "https://www.boost.org/libs/unordered",
      "licenseConcluded": "BSL-1.0",
      "licenseDeclared": "NOASSERTION",
      "copyrightText": "NOASSERTION",
      "description": "Boost unordered module",
      "comment": "This is the port (recipe) consumed by vcpkg."
    },
    {
      "name": "boost-unordered:x64-linux",
      "SPDXID": "SPDXRef-binary",
      "versionInfo": "214f87f86cf7ceb916d860595b3d219466f590fee297bf83831ad9c01b919ad0",
      "downloadLocation": "NONE",
      "licenseConcluded": "BSL-1.0",
      "licenseDeclared": "NOASSERTION",
      "copyrightText": "NOASSERTION",
      "comment": "This is a binary package built by vcpkg."
    },
    {
      "SPDXID": "SPDXRef-resource-0",
      "name": "boostorg/unordered",
      "downloadLocation": "git+https://github.com/boostorg/unordered@boost-1.86.0",
      "licenseConcluded": "NOASSERTION",
      "licenseDeclared": "NOASSERTION",
      "copyrightText": "NOASSERTION",
      "checksums": [
        {
          "algorithm": "SHA512",
          "checksumValue": "65865639d5e3d9f323cfffbdf532224b1f06f2c04a6a25e7f282a4051814101835c71747642bf7a8a704b6fbcde9006b03abac2e5a1e185a205fc88c3b3394e1"
        }
      ]
    }
  ],
  "files": [
    {
      "fileName": ".//home/mamsds/bin/vcpkg/buildtrees/versioning_/versions/boost-unordered/3016f6768a087d2f7a5629edae86d00c67191f1f/portfile.cmake",
      "SPDXID": "SPDXRef-file-0",
      "checksums": [
        {
          "algorithm": "SHA256",
          "checksumValue": "0dbe9cda174e0f026b12feadcffc614e5a68569f13a32a04ea0c8c2dab44804f"
        }
      ],
      "licenseConcluded": "NOASSERTION",
      "copyrightText": "NOASSERTION"
    },
    {
      "fileName": ".//home/mamsds/bin/vcpkg/buildtrees/versioning_/versions/boost-unordered/3016f6768a087d2f7a5629edae86d00c67191f1f/vcpkg.json",
      "SPDXID": "SPDXRef-file-1",
      "checksums": [
        {
          "algorithm": "SHA256",
          "checksumValue": "4ae46021f508dd80686317f4a147569bc0d0eb875fd5917e09b75b18f10c990a"
        }
      ],
      "licenseConcluded": "NOASSERTION",
      "copyrightText": "NOASSERTION"
    }
  ]
}
